locust_plugin_result/__init__.py
locust_plugin_result/result.py
locust_plugin_result/web.py
locust_plugin_result-0.0.3.dist-info/LICENSE.txt
locust_plugin_result-0.0.3.dist-info/METADATA
locust_plugin_result-0.0.3.dist-info/WHEEL
locust_plugin_result-0.0.3.dist-info/top_level.txt
locust_plugin_result-0.0.3.dist-info/version.txt
locust_plugin_result-0.0.3.dist-info/version_full.txt
locust_plugin_result-0.0.3.dist-info/zip-safe
locust_plugin_result-0.0.3.dist-info/RECORD
