Metadata-Version: 2.1
Name: locust-plugin-result
Version: 0.0.3
Summary: Locust plugin for providing FAIL/PASS result of test run.
Home-page: https://github.com/lhupfeldt/locust-plugin-result
Author: Lars Hupfeldt Nielsen
Author-email: lhn@hupfeldtit.dk
License: BSD
Platform: UNKNOWN
Classifier: Development Status :: 3 - Alpha
Classifier: Environment :: Web Environment
Classifier: Intended Audience :: Developers
Classifier: License :: OSI Approved :: BSD License
Classifier: Natural Language :: English
Classifier: Operating System :: OS Independent
Classifier: Programming Language :: Python :: 3.6
Classifier: Programming Language :: Python :: 3.7
Classifier: Programming Language :: Python :: 3.8
Classifier: Topic :: Software Development :: Testing
Requires-Python: >=3.6.0
Requires-Dist: locust (>=1.2.3)
Requires-Dist: multiconf (>=9.1.1)
